pyfiredb
