Metadata-Version: 2.1
Name: pyfiredb
Version: 0.0.2
Summary: pyfire is a package that simplifies querying with Pyrebase,    making interactions with Firebase databases effortless.
Home-page: https://github.com/andresroh/pyfire
Author: Camilo Andrés Rodríguez
Author-email: andres.roh@gmail.com
License: MIT
Keywords: python,alegra,alegra.com
Platform: UNKNOWN
Classifier: Development Status :: 3 - Alpha
Classifier: Intended Audience :: Developers
Classifier: Topic :: Software Development :: Build Tools
Classifier: License :: OSI Approved :: MIT License
Classifier: Programming Language :: Python :: 3
License-File: LICENSE.txt
